unboil_sqlalchemy_utils/__init__.py
unboil_sqlalchemy_utils-0.1.3.dist-info/METADATA
unboil_sqlalchemy_utils-0.1.3.dist-info/WHEEL
unboil_sqlalchemy_utils-0.1.3.dist-info/licenses/LICENSE
unboil_sqlalchemy_utils-0.1.3.dist-info/RECORD
