Metadata-Version: 2.4
Name: unboil-sqlalchemy-utils
Version: 0.1.3
Summary: A library providing reusable utilities for SQLAlchemy.
Project-URL: homepage, https://github.com/eyueldk/unboil-sqlalchemy-utils
Project-URL: repository, https://github.com/eyueldk/unboil-sqlalchemy-utils
Author: eyueldk
License: MIT
License-File: LICENSE
Keywords: database,orm,python,reusable,sqlalchemy,unboil,utils
Classifier: License :: OSI Approved :: MIT License
Classifier: Operating System :: OS Independent
Classifier: Programming Language :: Python :: 3
Classifier: Programming Language :: Python :: 3.9
Requires-Python: >=3.9
Requires-Dist: sqlalchemy>=2.0.0
